MANIFEST.in
README.md
setup.py
vbigbang_proxy_utils/__init__.py
vbigbang_proxy_utils/__utils.py
vbigbang_proxy_utils/proxy_check.py
vbigbang_proxy_utils/proxy_utils.py
vbigbang_proxy_utils/qqwry.dat
vbigbang_proxy_utils.egg-info/PKG-INFO
vbigbang_proxy_utils.egg-info/SOURCES.txt
vbigbang_proxy_utils.egg-info/dependency_links.txt
vbigbang_proxy_utils.egg-info/not-zip-safe
vbigbang_proxy_utils.egg-info/requires.txt
vbigbang_proxy_utils.egg-info/top_level.txt