Metadata-Version: 2.1
Name: vbigbang-proxy-utils
Version: 1.0.9
Summary: Commonly used function library by MT
Home-page: https://github.com/vbigbang
Author: vbigbang
Author-email: i@chenxiaosa.com
License: GPL
Requires-Python: >=3
